MANIFEST.in
README.rst
setup.py
docs/HISTORY.txt
docs/INSTALL.txt
docs/LICENSE.GPL
docs/LICENSE.txt
monet/__init__.py
monet.calendar.event.egg-info/PKG-INFO
monet.calendar.event.egg-info/SOURCES.txt
monet.calendar.event.egg-info/dependency_links.txt
monet.calendar.event.egg-info/entry_points.txt
monet.calendar.event.egg-info/namespace_packages.txt
monet.calendar.event.egg-info/not-zip-safe
monet.calendar.event.egg-info/requires.txt
monet.calendar.event.egg-info/top_level.txt
monet/calendar/__init__.py
monet/calendar/event/README.txt
monet/calendar/event/__init__.py
monet/calendar/event/config.py
monet/calendar/event/configure.zcml
monet/calendar/event/extender.py
monet/calendar/event/indexers.py
monet/calendar/event/interfaces.py
monet/calendar/event/migrator.py
monet/calendar/event/setuphandler.py
monet/calendar/event/utils.py
monet/calendar/event/Extensions/install.py
monet/calendar/event/browser/__init__.py
monet/calendar/event/browser/calendar.py
monet/calendar/event/browser/configure.zcml
monet/calendar/event/browser/event_view.pt
monet/calendar/event/browser/migrateblobs.py
monet/calendar/event/browser/stylesheets/monetcalendarevent.css
monet/calendar/event/content/__init__.py
monet/calendar/event/content/base_recurring_event.py
monet/calendar/event/content/configure.zcml
monet/calendar/event/content/event.py
monet/calendar/event/locales/i18n.sh
monet/calendar/event/locales/monet.calendar.event.pot
monet/calendar/event/locales/it/LC_MESSAGES/monet.calendar.event.mo
monet/calendar/event/locales/it/LC_MESSAGES/monet.calendar.event.po
monet/calendar/event/profiles/default/browserlayer.xml
monet/calendar/event/profiles/default/catalog.xml
monet/calendar/event/profiles/default/metadata.xml
monet/calendar/event/profiles/default/monet.calendar.event-various.txt
monet/calendar/event/profiles/default/propertiestool.xml
monet/calendar/event/profiles/default/types.xml
monet/calendar/event/profiles/default/types/Event.xml
monet/calendar/event/profiles/default/types/Topic.xml
monet/calendar/event/profiles/uninstall/types.xml
monet/calendar/event/profiles/uninstall/types/Event.xml
monet/calendar/event/tests/__init__.py
monet/calendar/event/tests/base.py
monet/calendar/event/tests/test_doctest.py